{"tasks":{"2026-07-13":{"d1":{"assignee":null,"joint":true,"claims":["dad","mom"],"completedBy":["dad","mom"],"done":true,"doneTime":"16:01:56","actualDad":1,"actualMom":1},"d2":{"assignee":"mom","joint":false,"claims":["mom"],"completedBy":["mom"],"done":true,"doneTime":"16:02:04","actualMom":2},"d3":{"assignee":"mom","joint":false,"claims":["mom"],"completedBy":["mom"],"done":true,"doneTime":"16:02:05","actualMom":2},"d4":{"assignee":"mom","joint":false,"claims":["mom"],"completedBy":["mom"],"done":true,"doneTime":"16:02:07","actualMom":3},"d5":{"assignee":"dad","joint":false,"claims":["dad"],"completedBy":["dad"],"done":true,"doneTime":"16:02:08","actualDad":3}},"2026-07-14":{"w1":{"assignee":null,"joint":false,"claims":[],"completedBy":[],"done":false,"doneTime":null},"w2":{"assignee":"mom","joint":false,"claims":["mom"],"completedBy":["mom"],"done":true,"doneTime":"21:49:21","actualMom":1},"w3":{"assignee":null,"joint":false,"claims":[],"completedBy":[],"done":false,"doneTime":null},"d1":{"assignee":"mom","joint":false,"claims":["mom"],"completedBy":["mom"],"done":true,"doneTime":"21:48:15","actualMom":1},"d2":{"assignee":null,"joint":false,"claims":[],"completedBy":[],"done":false,"doneTime":null},"d3":{"assignee":"mom","joint":false,"claims":["mom"],"completedBy":["mom"],"done":true,"doneTime":"21:48:26","actualMom":2},"d4":{"assignee":null,"joint":false,"claims":[],"completedBy":[],"done":false,"doneTime":null},"d5":{"assignee":null,"joint":true,"claims":["dad","mom"],"completedBy":["dad","mom"],"done":true,"doneTime":"22:36:51","actualDad":1,"actualMom":1}},"2026-07-15":{"d1":{"assignee":"mom","joint":false,"claims":["mom"],"completedBy":["mom"],"done":true,"doneTime":"21:44:45","actualMom":90},"d2":{"assignee":null,"joint":true,"claims":["dad","mom"],"completedBy":["dad","mom"],"done":true,"doneTime":"22:10:57","actualMom":15,"actualDad":15},"d3":{"assignee":"mom","joint":false,"claims":["mom"],"completedBy":["mom"],"done":true,"doneTime":"21:45:05","actualMom":15},"d4":{"assignee":null,"joint":true,"claims":["dad","mom"],"completedBy":["dad","mom"],"done":true,"doneTime":"21:45:19","actualMom":20},"d5":{"assignee":"mom","joint":false,"claims":["mom"],"completedBy":["mom"],"done":true,"doneTime":"21:48:49","actualMom":10},"w2":{"assignee":"mom","joint":false,"claims":["mom"],"completedBy":["mom"],"done":true,"doneTime":"22:52:48"}},"2026-07-17":{"d1":{"assignee":null,"joint":true,"claims":["dad","mom"],"completedBy":["dad","mom"],"done":true,"doneTime":"20:47:56","actualDad":120,"actualMom":120},"d2":{"assignee":"dad","joint":false,"claims":["dad"],"completedBy":["dad"],"done":true,"doneTime":"20:48:21","actualDad":20},"d3":{"assignee":"mom","joint":false,"claims":["mom"],"completedBy":["mom"],"done":true,"doneTime":"20:48:28","actualMom":20},"d4":{"assignee":"mom","joint":false,"claims":["mom"],"completedBy":["mom"],"done":true,"doneTime":"20:50:13","actualMom":20},"d5":{"assignee":"mom","joint":false,"claims":["mom"],"completedBy":["mom"],"done":true,"doneTime":"20:50:24","actualMom":20},"w2":{"assignee":"mom","joint":false,"claims":["mom"],"completedBy":["mom"],"done":true,"doneTime":"21:54:33"}},"2026-07-18":{"d1":{"assignee":"mom","joint":false,"claims":["mom"],"completedBy":["mom"],"done":true,"doneTime":"15:48:39","actualMom":120},"d3":{"assignee":null,"joint":true,"claims":["dad","mom"],"completedBy":["dad","mom"],"done":true,"doneTime":"15:48:57","actualDad":5,"actualMom":5},"d4":{"assignee":null,"joint":true,"claims":["dad","mom"],"completedBy":["dad","mom"],"done":true,"doneTime":"15:49:19","actualDad":10,"actualMom":10},"d5":{"assignee":null,"joint":true,"claims":["dad","mom"],"completedBy":["dad","mom"],"done":true,"doneTime":"15:49:33","actualDad":5,"actualMom":5},"d2":{"assignee":null,"joint":true,"claims":["dad","mom"],"completedBy":["dad","mom"],"done":true,"doneTime":"15:50:11","actualMom":10},"s1":{"assignee":null,"joint":true,"claims":["dad","mom"],"completedBy":["dad","mom"],"done":true,"doneTime":"15:50:53","actualDad":60,"actualMom":60}},"2026-07-19":{"d5":{"assignee":"mom","joint":false,"claims":["mom"],"completedBy":["mom"],"done":true,"doneTime":"10:34:26","actualMom":10},"d2":{"assignee":null,"joint":true,"claims":["dad","mom"],"completedBy":["dad","mom"],"done":true,"doneTime":"10:34:33","actualMom":10},"w3":{"assignee":"mom","joint":false,"claims":["mom"],"completedBy":["mom"],"done":true,"doneTime":"10:34:49"}}},"rules":null,"deducts":{"dad":{"2026-07-15":[{"name":"玩游戏","minutes":45}],"2026-07-19":[],"2026-07-18":[{"name":"和朋友打麻将聚餐","minutes":270}]},"mom":{"2026-07-15":[{"name":"陪伴","minutes":20}]}},"weekend":{"2026-07-18":{}},"log":[{"time":"2026/7/19 10:34:49","operator":"mom","date":"2026-07-19","action":"认领打卡","detail":"地面清洁与卫生间维护 · 妈妈完成"},{"time":"2026/7/19 10:34:39","operator":"mom","date":"2026-07-19","action":"修改耗时","detail":"检查作业：语文（每日一练、练字、背诵古诗） · 妈妈10分钟"},{"time":"2026/7/19 10:34:33","operator":"mom","date":"2026-07-19","action":"认领打卡","detail":"检查作业：语文（每日一练、练字、背诵古诗） · 共同完成"},{"time":"2026/7/19 10:34:30","operator":"mom","date":"2026-07-19","action":"修改耗时","detail":"衣物洗晾与收纳 · 妈妈10分钟"},{"time":"2026/7/19 10:34:26","operator":"mom","date":"2026-07-19","action":"认领打卡","detail":"衣物洗晾与收纳 · 妈妈完成"},{"time":"2026/7/19 00:10:25","operator":"mom","date":"2026-07-18","action":"修改扣减","detail":"爸爸 · 270分钟"},{"time":"2026/7/19 00:10:22","operator":"mom","date":"2026-07-18","action":"修改扣减","detail":"和朋友打麻将聚餐"},{"time":"2026/7/19 00:10:14","operator":"mom","date":"2026-07-18","action":"添加扣减","detail":"爸爸 · 30分钟"},{"time":"2026/7/19 00:10:05","operator":"mom","date":"2026-07-19","action":"删除扣减","detail":"爸爸 · 和朋友聚餐打麻将 270分钟"},{"time":"2026/7/19 00:09:29","operator":"mom","date":"2026-07-19","action":"修改扣减","detail":"爸爸 · 270分钟"},{"time":"2026/7/19 00:08:22","operator":"mom","date":"2026-07-19","action":"修改扣减","detail":"和朋友聚餐打麻将"},{"time":"2026/7/19 00:08:12","operator":"mom","date":"2026-07-19","action":"添加扣减","detail":"爸爸 · 30分钟"},{"time":"2026/7/18 15:51:05","operator":"dad","date":"2026-07-18","action":"修改耗时","detail":"带玩（约朋友、共同陪伴、关注安全） · 妈妈60分钟"},{"time":"2026/7/18 15:51:03","operator":"dad","date":"2026-07-18","action":"修改耗时","detail":"带玩（约朋友、共同陪伴、关注安全） · 爸爸60分钟"},{"time":"2026/7/18 15:50:53","operator":"dad","date":"2026-07-18","action":"认领打卡","detail":"带玩（约朋友、共同陪伴、关注安全） · 共同完成"},{"time":"2026/7/18 15:50:17","operator":"dad","date":"2026-07-18","action":"修改耗时","detail":"检查作业：语文（每日一练、练字、背诵古诗） · 妈妈10分钟"},{"time":"2026/7/18 15:50:11","operator":"dad","date":"2026-07-18","action":"认领打卡","detail":"检查作业：语文（每日一练、练字、背诵古诗） · 共同完成"},{"time":"2026/7/18 15:49:50","operator":"dad","date":"2026-07-18","action":"认领打卡","detail":"检查作业：语文（每日一练、练字、背诵古诗） · 爸爸完成"},{"time":"2026/7/18 15:49:40","operator":"dad","date":"2026-07-18","action":"修改耗时","detail":"衣物洗晾与收纳 · 妈妈5分钟"},{"time":"2026/7/18 15:49:38","operator":"dad","date":"2026-07-18","action":"修改耗时","detail":"衣物洗晾与收纳 · 爸爸5分钟"},{"time":"2026/7/18 15:49:33","operator":"dad","date":"2026-07-18","action":"认领打卡","detail":"衣物洗晾与收纳 · 共同完成"},{"time":"2026/7/18 15:49:33","operator":"dad","date":"2026-07-18","action":"修改耗时","detail":"检查作业：数学（每日一练、口算、九九乘法表） · 妈妈10分钟"},{"time":"2026/7/18 15:49:19","operator":"dad","date":"2026-07-18","action":"认领打卡","detail":"检查作业：数学（每日一练、口算、九九乘法表） · 共同完成"},{"time":"2026/7/18 15:49:19","operator":"dad","date":"2026-07-18","action":"修改耗时","detail":"检查作业：数学（每日一练、口算、九九乘法表） · 爸爸10分钟"},{"time":"2026/7/18 15:49:12","operator":"dad","date":"2026-07-18","action":"认领打卡","detail":"检查作业：数学（每日一练、口算、九九乘法表） · 爸爸完成"},{"time":"2026/7/18 15:49:10","operator":"dad","date":"2026-07-18","action":"修改耗时","detail":"检查作业：英语（App打卡、WowEnglish、磨耳朵、字母、字帖） · 妈妈5分钟"},{"time":"2026/7/18 15:49:03","operator":"dad","date":"2026-07-18","action":"修改耗时","detail":"检查作业：英语（App打卡、WowEnglish、磨耳朵、字母、字帖） · 爸爸5分钟"},{"time":"2026/7/18 15:48:57","operator":"dad","date":"2026-07-18","action":"认领打卡","detail":"检查作业：英语（App打卡、WowEnglish、磨耳朵、字母、字帖） · 共同完成"},{"time":"2026/7/18 15:48:45","operator":"dad","date":"2026-07-18","action":"修改耗时","detail":"带游泳课 / 户外运动 · 妈妈120分钟"},{"time":"2026/7/18 15:48:39","operator":"dad","date":"2026-07-18","action":"认领打卡","detail":"带游泳课 / 户外运动 · 妈妈完成"},{"time":"2026/7/17 21:54:33","operator":"mom","date":"2026-07-17","action":"认领打卡","detail":"带睡觉（液体钙、刷牙、睡前故事） · 妈妈完成"},{"time":"2026/7/17 21:54:33","operator":"mom","date":"2026-07-17","action":"取消认领","detail":"带睡觉（液体钙、刷牙、睡前故事） · 取消爸爸"},{"time":"2026/7/17 21:54:32","operator":"mom","date":"2026-07-17","action":"认领打卡","detail":"带睡觉（液体钙、刷牙、睡前故事） · 爸爸完成"},{"time":"2026/7/17 20:50:30","operator":"mom","date":"2026-07-17","action":"修改耗时","detail":"衣物洗晾与收纳 · 妈妈20分钟"},{"time":"2026/7/17 20:50:24","operator":"mom","date":"2026-07-17","action":"认领打卡","detail":"衣物洗晾与收纳 · 妈妈完成"},{"time":"2026/7/17 20:50:22","operator":"mom","date":"2026-07-17","action":"修改耗时","detail":"检查作业：数学（每日一练、口算、九九乘法表） · 妈妈20分钟"},{"time":"2026/7/17 20:50:13","operator":"mom","date":"2026-07-17","action":"认领打卡","detail":"检查作业：数学（每日一练、口算、九九乘法表） · 妈妈完成"},{"time":"2026/7/17 20:50:13","operator":"mom","date":"2026-07-17","action":"修改耗时","detail":"检查作业：英语（App打卡、WowEnglish、磨耳朵、字母、字帖） · 妈妈20分钟"},{"time":"2026/7/17 20:48:28","operator":"mom","date":"2026-07-17","action":"认领打卡","detail":"检查作业：英语（App打卡、WowEnglish、磨耳朵、字母、字帖） · 妈妈完成"},{"time":"2026/7/17 20:48:27","operator":"mom","date":"2026-07-17","action":"修改耗时","detail":"检查作业：语文（每日一练、练字、背诵古诗） · 爸爸20分钟"},{"time":"2026/7/17 20:48:21","operator":"mom","date":"2026-07-17","action":"认领打卡","detail":"检查作业：语文（每日一练、练字、背诵古诗） · 爸爸完成"},{"time":"2026/7/17 20:48:18","operator":"mom","date":"2026-07-17","action":"修改耗时","detail":"带游泳课 / 户外运动 · 妈妈120分钟"},{"time":"2026/7/17 20:48:14","operator":"mom","date":"2026-07-17","action":"修改耗时","detail":"带游泳课 / 户外运动 · 爸爸120分钟"},{"time":"2026/7/17 20:47:56","operator":"mom","date":"2026-07-17","action":"认领打卡","detail":"带游泳课 / 户外运动 · 共同完成"},{"time":"2026/7/16 14:26:55","operator":"mom","date":"2026-07-14","action":"修改耗时","detail":"带睡觉（液体钙、刷牙、睡前故事） · 妈妈1分钟"},{"time":"2026/7/16 14:26:48","operator":"mom","date":"2026-07-14","action":"修改耗时","detail":"衣物洗晾与收纳 · 妈妈1分钟"},{"time":"2026/7/16 14:26:46","operator":"mom","date":"2026-07-14","action":"修改耗时","detail":"衣物洗晾与收纳 · 爸爸1分钟"},{"time":"2026/7/16 14:26:43","operator":"mom","date":"2026-07-14","action":"修改耗时","detail":"检查作业：英语（App打卡、WowEnglish、磨耳朵、字母、字帖） · 妈妈2分钟"},{"time":"2026/7/16 14:26:39","operator":"mom","date":"2026-07-14","action":"修改耗时","detail":"带游泳课 / 户外运动 · 妈妈1分钟"},{"time":"2026/7/16 14:25:43","operator":"mom","date":"2026-07-13","action":"修改耗时","detail":"衣物洗晾与收纳 · 爸爸3分钟"},{"time":"2026/7/16 14:25:41","operator":"mom","date":"2026-07-13","action":"修改耗时","detail":"检查作业：数学（每日一练、口算、九九乘法表） · 妈妈3分钟"},{"time":"2026/7/16 14:25:39","operator":"mom","date":"2026-07-13","action":"修改耗时","detail":"检查作业：英语（App打卡、WowEnglish、磨耳朵、字母、字帖） · 妈妈2分钟"},{"time":"2026/7/16 14:25:37","operator":"mom","date":"2026-07-13","action":"修改耗时","detail":"检查作业：语文（每日一练、练字、背诵古诗） · 妈妈2分钟"},{"time":"2026/7/16 14:25:31","operator":"mom","date":"2026-07-13","action":"修改耗时","detail":"带游泳课 / 户外运动 · 妈妈1分钟"},{"time":"2026/7/16 14:25:28","operator":"mom","date":"2026-07-13","action":"修改耗时","detail":"带游泳课 / 户外运动 · 爸爸1分钟"},{"time":"2026/7/16 00:05:40","operator":"mom","date":"2026-07-15","action":"修改扣减","detail":"妈妈 · 20分钟"},{"time":"2026/7/16 00:04:59","operator":"mom","date":"2026-07-15","action":"修改扣减","detail":"陪伴"},{"time":"2026/7/16 00:04:52","operator":"mom","date":"2026-07-15","action":"添加扣减","detail":"妈妈 · 30分钟"},{"time":"2026/7/15 22:57:24","operator":"mom","date":"2026-07-15","action":"修改扣减","detail":"爸爸 · 45分钟"},{"time":"2026/7/15 22:57:20","operator":"mom","date":"2026-07-15","action":"修改扣减","detail":"玩游戏"},{"time":"2026/7/15 22:57:16","operator":"mom","date":"2026-07-15","action":"添加扣减","detail":"爸爸 · 30分钟"},{"time":"2026/7/15 22:52:48","operator":"mom","date":"2026-07-15","action":"认领打卡","detail":"带睡觉（液体钙、刷牙、睡前故事） · 妈妈完成"},{"time":"2026/7/15 22:11:02","operator":"mom","date":"2026-07-15","action":"修改耗时","detail":"检查作业：语文（每日一练、练字、背诵古诗） · 爸爸15分钟"},{"time":"2026/7/15 22:10:57","operator":"mom","date":"2026-07-15","action":"认领打卡","detail":"检查作业：语文（每日一练、练字、背诵古诗） · 共同完成"},{"time":"2026/7/15 21:48:55","operator":"mom","date":"2026-07-15","action":"修改耗时","detail":"衣物洗晾与收纳 · 妈妈10分钟"},{"time":"2026/7/15 21:48:49","operator":"mom","date":"2026-07-15","action":"认领打卡","detail":"衣物洗晾与收纳 · 妈妈完成"},{"time":"2026/7/15 21:45:28","operator":"mom","date":"2026-07-15","action":"修改耗时","detail":"检查作业：数学（每日一练、口算、九九乘法表） · 妈妈20分钟"},{"time":"2026/7/15 21:45:19","operator":"mom","date":"2026-07-15","action":"认领打卡","detail":"检查作业：数学（每日一练、口算、九九乘法表） · 共同完成"},{"time":"2026/7/15 21:45:10","operator":"mom","date":"2026-07-15","action":"修改耗时","detail":"检查作业：英语（App打卡、WowEnglish、磨耳朵、字母、字帖） · 妈妈15分钟"},{"time":"2026/7/15 21:45:05","operator":"mom","date":"2026-07-15","action":"认领打卡","detail":"检查作业：英语（App打卡、WowEnglish、磨耳朵、字母、字帖） · 妈妈完成"},{"time":"2026/7/15 21:45:01","operator":"mom","date":"2026-07-15","action":"修改耗时","detail":"检查作业：语文（每日一练、练字、背诵古诗） · 妈妈15分钟"},{"time":"2026/7/15 21:44:56","operator":"mom","date":"2026-07-15","action":"认领打卡","detail":"检查作业：语文（每日一练、练字、背诵古诗） · 妈妈完成"},{"time":"2026/7/15 21:44:52","operator":"mom","date":"2026-07-15","action":"修改耗时","detail":"带游泳课 / 户外运动 · 妈妈90分钟"},{"time":"2026/7/15 21:44:45","operator":"mom","date":"2026-07-15","action":"认领打卡","detail":"带游泳课 / 户外运动 · 妈妈完成"}],"timestamp":1784428490936}